MANIFEST.in
NEWS.txt
setup.py
src/savepoint/__init__.py
src/savepoint.egg-info/PKG-INFO
src/savepoint.egg-info/SOURCES.txt
src/savepoint.egg-info/dependency_links.txt
src/savepoint.egg-info/not-zip-safe
src/savepoint.egg-info/top_level.txt