Metadata-Version: 1.0
Name: savepoint
Version: 0.1
Summary: A context manager that creates savepoints
Home-page: UNKNOWN
Author: Roberto De Almeida
Author-email: roberto@dealmeida.net
License: MIT
Keywords: context manager savepoint hack
Platform: UNKNOWN
